api/__init__.py
api/client.py
api/server.py
core/__init__.py
core/artifact.py
core/config.py
core/experiment.py
core/system_monitor.py
integrations/__init__.py
integrations/pytorch.py
integrations/sklearn.py
integrations/tensorflow.py
storage/__init__.py
storage/cloud.py
storage/local.py
utils/__init__.py
utils/logging.py
utils/serialization.py
visualization/__init__.py
visualization/dashboard.py
visualization/plots.py
dotmltracker-0.1.0.dist-info/METADATA
dotmltracker-0.1.0.dist-info/WHEEL
dotmltracker-0.1.0.dist-info/top_level.txt
dotmltracker-0.1.0.dist-info/RECORD
