Metadata-Version: 2.4
Name: dotmltracker
Version: 0.1.0
Summary: A comprehensive ML experiment tracking library
Home-page: https://github.com/yourusername/mltracker
Author: Suvadip Chakraborty
Author-email: suvadipchakraborty2006@gmail.com
Classifier: Programming Language :: Python :: 3
Classifier: License :: OSI Approved :: MIT License
Classifier: Operating System :: OS Independent
Requires-Python: >=3.6
Requires-Dist: numpy
Requires-Dist: matplotlib
Requires-Dist: flask
Requires-Dist: psutil
Requires-Dist: pillow
Requires-Dist: requests
Provides-Extra: pytorch
Requires-Dist: torch; extra == "pytorch"
Provides-Extra: tensorflow
Requires-Dist: tensorflow; extra == "tensorflow"
Provides-Extra: sklearn
Requires-Dist: scikit-learn; extra == "sklearn"
Provides-Extra: cloud
Requires-Dist: boto3; extra == "cloud"
Provides-Extra: gpu
Requires-Dist: GPUtil; extra == "gpu"
Dynamic: author
Dynamic: author-email
Dynamic: classifier
Dynamic: description
Dynamic: description-content-type
Dynamic: home-page
Dynamic: provides-extra
Dynamic: requires-dist
Dynamic: requires-python
Dynamic: summary
